{
  "header": { "title": "My Event" },
  "add_new": "Add new event",
  "export_csv": "Export CSV",
  "event_label": "Event",
  "management": {
    "label_event": "Events",
    "label_status": "Status",
    "label_category": "Category",
    "label_price": "Price",
    "search": "Search ...",
    "view_events": "View events",
    "select_action": "Select Action",
    "button_edit": "Edit",
    "button_restore": "Restore",
    "button_trash": "Trash",
    "button_delete": "Delete",
    "apply_coupons": "Apply Coupons"
  },
  "apply_coupon": {
    "title": "Apply coupon",
    "apply": "Apply"
  }
}
