{
  "header": {
    "title": "Explorer"
  },
  "sort": "Trier par date",
  "asc": "Ascendant",
  "desc": "Descendant",
  "search": "Rechercher ...",
  "sidebar": {
    "rate": {
      "label": "Évaluation",
      "star": "étoile"
    },
    "status": {
      "label": "Statut",
      "all": "Tous",
      "upcoming": "À venir",
      "opening": "Ouvert",
      "closed": "Fermé"
    },
    "category": {
      "label": "Catégorie",
      "Business": "Affaires",
      "Gaming": "Jeux",
      "Food & Beverage": "Aliments et Boissons",
      "Education": "Éducation",
      "Home & Garden": "Maison et Jardin",
      "Parenting": "Parentalité",
      "Fashion": "Mode",
      "Travel": "Voyages",
      "Finance & Investment": "Finance et Investissement",
      "Movies & TV": "Films et TV",
      "Books & Literature": "Livres et Littérature",
      "Photography": "Photographie",
      "Sport": "Sport",
      "Music": "Musique",
      "Pet & Animals": "Animaux et Animaux de Compagnie",
      "Health & Fitness": "Santé et Fitness",
      "Art & Design": "Art et Design",
      "Science": "Science",
      "Technology": "Technologie",
      "Personal Development": "Développement Personnel"
    }
  }
}
